setup.py
gradio_academic_agents.egg-info/PKG-INFO
gradio_academic_agents.egg-info/SOURCES.txt
gradio_academic_agents.egg-info/dependency_links.txt
gradio_academic_agents.egg-info/top_level.txt
test_data/__init__.py
test_data/blocks_configs.py
themes/__init__.py
themes/app.py
themes/base.py
themes/builder_app.py
themes/default.py
themes/glass.py
themes/monochrome.py
themes/soft.py
themes/upload_theme.py
themes/utils/__init__.py
themes/utils/colors.py
themes/utils/fonts.py
themes/utils/readme_content.py
themes/utils/semver_match.py
themes/utils/sizes.py
themes/utils/theme_dropdown.py