Metadata-Version: 2.1
Name: gradio_academic_agents
Version: 1.0.1
Summary: gradio for academic agents studio
Home-page: https://github.com/AcademicAgentsStudio
Author: AIOAGI
Author-email: aioagi@aioagi.tech
Classifier: Programming Language :: Python :: 3
